{
    "event_numbers": [
        458400,
        458401,
        458402,
        458403,
        458404,
        458405,
        458406,
        458407,
        458408,
        458409,
        458410,
        458411,
        458412,
        458413,
        458414,
        458415,
        458416,
        458417,
        458418,
        458419,
        458420,
        458421,
        458422,
        458423,
        458424,
        458425,
        458426,
        458427,
        458428,
        458429,
        458430,
        458431,
        458432,
        458433,
        458434,
        458435,
        458436,
        458437,
        458438,
        458439,
        458440,
        458441,
        458442,
        458443,
        458444,
        458445,
        458446,
        458447,
        458448,
        458449,
        458450,
        458451,
        458452,
        458453,
        458454,
        458455,
        458456,
        458457,
        458458,
        458459,
        458460,
        458461,
        458462,
        458463,
        458464,
        458465,
        458466,
        458467,
        458468,
        458469,
        458470,
        458471,
        458472,
        458473,
        458474,
        458475,
        458476,
        458477,
        458478,
        458479,
        458480,
        458481,
        458482,
        458483,
        458484,
        458485,
        458486,
        458487,
        458488,
        458489,
        458490,
        458491,
        458492,
        458493,
        458494,
        458495,
        458496,
        458497,
        458498,
        458499
    ],
    "job_id": 4584,
    "seed": 2347520,
    "particle_name": "Jpsi",
    "run": {
        "nov": 100,
        "nov_per_job": 100,
        "run_number": 20250122,
        "seed": 512
    },
    "stages": [
        {
            "name": "step_1",
            "script": "gen_Jpsi.py",
            "extra_args": {
                "seed": "%SEED",
                "run-number": "%RUN_NUMBER",
                "event-numbers": "%EVENT_NUMBERS"
            },
            "output": "%JOB_WORKAREA/step_1/Jpsi.EVT.%JOB_ID.root"
        },
        {
            "name": "step_2",
            "script": "simu_trf.py",
            "extra_args": {
                "enable-magnetic-field": "None",
                "timeout": 30,
                "number-of-threads": "%CPU_CORES"
            },
            "input": "%JOB_WORKAREA/step_1/Jpsi.EVT.%JOB_ID.root",
            "output": "%JOB_WORKAREA/step_2/Jpsi.HIT.%JOB_ID.root"
        },
        {
            "name": "step_3",
            "script": "digit_trf.py",
            "extra_args": {},
            "input": "%JOB_WORKAREA/step_2/Jpsi.HIT.%JOB_ID.root",
            "output": "%JOB_WORKAREA/step_3/Jpsi.ESD.%JOB_ID.root"
        },
        {
            "name": "step_4",
            "script": "reco_trf.py",
            "extra_args": {},
            "input": "%JOB_WORKAREA/step_3/Jpsi.ESD.%JOB_ID.root",
            "output": "%JOB_WORKAREA/step_4/Jpsi.AOD.%JOB_ID.root"
        },
        {
            "name": "step_5",
            "script": "ntuple_trf.py",
            "extra_args": {},
            "input": "%JOB_WORKAREA/step_4/Jpsi.AOD.%JOB_ID.root",
            "output": "%JOB_WORKAREA/step_5/Jpsi.NTUP.%JOB_ID.root"
        }
    ]
}