{
    "event_numbers": [
        810700,
        810701,
        810702,
        810703,
        810704,
        810705,
        810706,
        810707,
        810708,
        810709,
        810710,
        810711,
        810712,
        810713,
        810714,
        810715,
        810716,
        810717,
        810718,
        810719,
        810720,
        810721,
        810722,
        810723,
        810724,
        810725,
        810726,
        810727,
        810728,
        810729,
        810730,
        810731,
        810732,
        810733,
        810734,
        810735,
        810736,
        810737,
        810738,
        810739,
        810740,
        810741,
        810742,
        810743,
        810744,
        810745,
        810746,
        810747,
        810748,
        810749,
        810750,
        810751,
        810752,
        810753,
        810754,
        810755,
        810756,
        810757,
        810758,
        810759,
        810760,
        810761,
        810762,
        810763,
        810764,
        810765,
        810766,
        810767,
        810768,
        810769,
        810770,
        810771,
        810772,
        810773,
        810774,
        810775,
        810776,
        810777,
        810778,
        810779,
        810780,
        810781,
        810782,
        810783,
        810784,
        810785,
        810786,
        810787,
        810788,
        810789,
        810790,
        810791,
        810792,
        810793,
        810794,
        810795,
        810796,
        810797,
        810798,
        810799
    ],
    "job_id": 8107,
    "seed": 4151296,
    "particle_name": "Jpsi",
    "run": {
        "nov": 100,
        "nov_per_job": 100,
        "run_number": 20250122,
        "seed": 512
    },
    "stages": [
        {
            "name": "step_1",
            "script": "gen_Jpsi.py",
            "extra_args": {
                "seed": "%SEED",
                "run-number": "%RUN_NUMBER",
                "event-numbers": "%EVENT_NUMBERS"
            },
            "output": "%JOB_WORKAREA/step_1/Jpsi.EVT.%JOB_ID.root"
        },
        {
            "name": "step_2",
            "script": "simu_trf.py",
            "extra_args": {
                "enable-magnetic-field": "None",
                "timeout": 30,
                "number-of-threads": "%CPU_CORES"
            },
            "input": "%JOB_WORKAREA/step_1/Jpsi.EVT.%JOB_ID.root",
            "output": "%JOB_WORKAREA/step_2/Jpsi.HIT.%JOB_ID.root"
        },
        {
            "name": "step_3",
            "script": "digit_trf.py",
            "extra_args": {},
            "input": "%JOB_WORKAREA/step_2/Jpsi.HIT.%JOB_ID.root",
            "output": "%JOB_WORKAREA/step_3/Jpsi.ESD.%JOB_ID.root"
        },
        {
            "name": "step_4",
            "script": "reco_trf.py",
            "extra_args": {},
            "input": "%JOB_WORKAREA/step_3/Jpsi.ESD.%JOB_ID.root",
            "output": "%JOB_WORKAREA/step_4/Jpsi.AOD.%JOB_ID.root"
        },
        {
            "name": "step_5",
            "script": "ntuple_trf.py",
            "extra_args": {},
            "input": "%JOB_WORKAREA/step_4/Jpsi.AOD.%JOB_ID.root",
            "output": "%JOB_WORKAREA/step_5/Jpsi.NTUP.%JOB_ID.root"
        }
    ]
}