{
    "event_numbers": [
        868000,
        868001,
        868002,
        868003,
        868004,
        868005,
        868006,
        868007,
        868008,
        868009,
        868010,
        868011,
        868012,
        868013,
        868014,
        868015,
        868016,
        868017,
        868018,
        868019,
        868020,
        868021,
        868022,
        868023,
        868024,
        868025,
        868026,
        868027,
        868028,
        868029,
        868030,
        868031,
        868032,
        868033,
        868034,
        868035,
        868036,
        868037,
        868038,
        868039,
        868040,
        868041,
        868042,
        868043,
        868044,
        868045,
        868046,
        868047,
        868048,
        868049,
        868050,
        868051,
        868052,
        868053,
        868054,
        868055,
        868056,
        868057,
        868058,
        868059,
        868060,
        868061,
        868062,
        868063,
        868064,
        868065,
        868066,
        868067,
        868068,
        868069,
        868070,
        868071,
        868072,
        868073,
        868074,
        868075,
        868076,
        868077,
        868078,
        868079,
        868080,
        868081,
        868082,
        868083,
        868084,
        868085,
        868086,
        868087,
        868088,
        868089,
        868090,
        868091,
        868092,
        868093,
        868094,
        868095,
        868096,
        868097,
        868098,
        868099
    ],
    "job_id": 8680,
    "seed": 4444672,
    "particle_name": "Jpsi",
    "run": {
        "nov": 100,
        "nov_per_job": 100,
        "run_number": 20250122,
        "seed": 512
    },
    "stages": [
        {
            "name": "step_1",
            "script": "gen_Jpsi.py",
            "extra_args": {
                "seed": "%SEED",
                "run-number": "%RUN_NUMBER",
                "event-numbers": "%EVENT_NUMBERS"
            },
            "output": "%JOB_WORKAREA/step_1/Jpsi.EVT.%JOB_ID.root"
        },
        {
            "name": "step_2",
            "script": "simu_trf.py",
            "extra_args": {
                "enable-magnetic-field": "None",
                "timeout": 30,
                "number-of-threads": "%CPU_CORES"
            },
            "input": "%JOB_WORKAREA/step_1/Jpsi.EVT.%JOB_ID.root",
            "output": "%JOB_WORKAREA/step_2/Jpsi.HIT.%JOB_ID.root"
        },
        {
            "name": "step_3",
            "script": "digit_trf.py",
            "extra_args": {},
            "input": "%JOB_WORKAREA/step_2/Jpsi.HIT.%JOB_ID.root",
            "output": "%JOB_WORKAREA/step_3/Jpsi.ESD.%JOB_ID.root"
        },
        {
            "name": "step_4",
            "script": "reco_trf.py",
            "extra_args": {},
            "input": "%JOB_WORKAREA/step_3/Jpsi.ESD.%JOB_ID.root",
            "output": "%JOB_WORKAREA/step_4/Jpsi.AOD.%JOB_ID.root"
        },
        {
            "name": "step_5",
            "script": "ntuple_trf.py",
            "extra_args": {},
            "input": "%JOB_WORKAREA/step_4/Jpsi.AOD.%JOB_ID.root",
            "output": "%JOB_WORKAREA/step_5/Jpsi.NTUP.%JOB_ID.root"
        }
    ]
}