{
    "event_numbers": [
        300100,
        300101,
        300102,
        300103,
        300104,
        300105,
        300106,
        300107,
        300108,
        300109,
        300110,
        300111,
        300112,
        300113,
        300114,
        300115,
        300116,
        300117,
        300118,
        300119,
        300120,
        300121,
        300122,
        300123,
        300124,
        300125,
        300126,
        300127,
        300128,
        300129,
        300130,
        300131,
        300132,
        300133,
        300134,
        300135,
        300136,
        300137,
        300138,
        300139,
        300140,
        300141,
        300142,
        300143,
        300144,
        300145,
        300146,
        300147,
        300148,
        300149,
        300150,
        300151,
        300152,
        300153,
        300154,
        300155,
        300156,
        300157,
        300158,
        300159,
        300160,
        300161,
        300162,
        300163,
        300164,
        300165,
        300166,
        300167,
        300168,
        300169,
        300170,
        300171,
        300172,
        300173,
        300174,
        300175,
        300176,
        300177,
        300178,
        300179,
        300180,
        300181,
        300182,
        300183,
        300184,
        300185,
        300186,
        300187,
        300188,
        300189,
        300190,
        300191,
        300192,
        300193,
        300194,
        300195,
        300196,
        300197,
        300198,
        300199
    ],
    "job_id": 3001,
    "seed": 1537024,
    "particle_name": "Jpsi",
    "run": {
        "nov": 100,
        "nov_per_job": 100,
        "run_number": 20250122,
        "seed": 512
    },
    "stages": [
        {
            "name": "step_1",
            "script": "gen_Jpsi.py",
            "extra_args": {
                "seed": "%SEED",
                "run-number": "%RUN_NUMBER",
                "event-numbers": "%EVENT_NUMBERS"
            },
            "output": "%JOB_WORKAREA/step_1/Jpsi.EVT.%JOB_ID.root"
        },
        {
            "name": "step_2",
            "script": "simu_trf.py",
            "extra_args": {
                "enable-magnetic-field": "None",
                "timeout": 30,
                "number-of-threads": "%CPU_CORES"
            },
            "input": "%JOB_WORKAREA/step_1/Jpsi.EVT.%JOB_ID.root",
            "output": "%JOB_WORKAREA/step_2/Jpsi.HIT.%JOB_ID.root"
        },
        {
            "name": "step_3",
            "script": "digit_trf.py",
            "extra_args": {},
            "input": "%JOB_WORKAREA/step_2/Jpsi.HIT.%JOB_ID.root",
            "output": "%JOB_WORKAREA/step_3/Jpsi.ESD.%JOB_ID.root"
        },
        {
            "name": "step_4",
            "script": "reco_trf.py",
            "extra_args": {},
            "input": "%JOB_WORKAREA/step_3/Jpsi.ESD.%JOB_ID.root",
            "output": "%JOB_WORKAREA/step_4/Jpsi.AOD.%JOB_ID.root"
        },
        {
            "name": "step_5",
            "script": "ntuple_trf.py",
            "extra_args": {},
            "input": "%JOB_WORKAREA/step_4/Jpsi.AOD.%JOB_ID.root",
            "output": "%JOB_WORKAREA/step_5/Jpsi.NTUP.%JOB_ID.root"
        }
    ]
}