{
    "event_numbers": [
        106200,
        106201,
        106202,
        106203,
        106204,
        106205,
        106206,
        106207,
        106208,
        106209,
        106210,
        106211,
        106212,
        106213,
        106214,
        106215,
        106216,
        106217,
        106218,
        106219,
        106220,
        106221,
        106222,
        106223,
        106224,
        106225,
        106226,
        106227,
        106228,
        106229,
        106230,
        106231,
        106232,
        106233,
        106234,
        106235,
        106236,
        106237,
        106238,
        106239,
        106240,
        106241,
        106242,
        106243,
        106244,
        106245,
        106246,
        106247,
        106248,
        106249,
        106250,
        106251,
        106252,
        106253,
        106254,
        106255,
        106256,
        106257,
        106258,
        106259,
        106260,
        106261,
        106262,
        106263,
        106264,
        106265,
        106266,
        106267,
        106268,
        106269,
        106270,
        106271,
        106272,
        106273,
        106274,
        106275,
        106276,
        106277,
        106278,
        106279,
        106280,
        106281,
        106282,
        106283,
        106284,
        106285,
        106286,
        106287,
        106288,
        106289,
        106290,
        106291,
        106292,
        106293,
        106294,
        106295,
        106296,
        106297,
        106298,
        106299
    ],
    "job_id": 1062,
    "seed": 544256,
    "particle_name": "Jpsi",
    "run": {
        "nov": 100,
        "nov_per_job": 100,
        "run_number": 20250122,
        "seed": 512
    },
    "stages": [
        {
            "name": "step_1",
            "script": "gen_Jpsi.py",
            "extra_args": {
                "seed": "%SEED",
                "run-number": "%RUN_NUMBER",
                "event-numbers": "%EVENT_NUMBERS"
            },
            "output": "%JOB_WORKAREA/step_1/Jpsi.EVT.%JOB_ID.root"
        },
        {
            "name": "step_2",
            "script": "simu_trf.py",
            "extra_args": {
                "enable-magnetic-field": "None",
                "timeout": 30,
                "number-of-threads": "%CPU_CORES"
            },
            "input": "%JOB_WORKAREA/step_1/Jpsi.EVT.%JOB_ID.root",
            "output": "%JOB_WORKAREA/step_2/Jpsi.HIT.%JOB_ID.root"
        },
        {
            "name": "step_3",
            "script": "digit_trf.py",
            "extra_args": {},
            "input": "%JOB_WORKAREA/step_2/Jpsi.HIT.%JOB_ID.root",
            "output": "%JOB_WORKAREA/step_3/Jpsi.ESD.%JOB_ID.root"
        },
        {
            "name": "step_4",
            "script": "reco_trf.py",
            "extra_args": {},
            "input": "%JOB_WORKAREA/step_3/Jpsi.ESD.%JOB_ID.root",
            "output": "%JOB_WORKAREA/step_4/Jpsi.AOD.%JOB_ID.root"
        },
        {
            "name": "step_5",
            "script": "ntuple_trf.py",
            "extra_args": {},
            "input": "%JOB_WORKAREA/step_4/Jpsi.AOD.%JOB_ID.root",
            "output": "%JOB_WORKAREA/step_5/Jpsi.NTUP.%JOB_ID.root"
        }
    ]
}