{
    "event_numbers": [
        107600,
        107601,
        107602,
        107603,
        107604,
        107605,
        107606,
        107607,
        107608,
        107609,
        107610,
        107611,
        107612,
        107613,
        107614,
        107615,
        107616,
        107617,
        107618,
        107619,
        107620,
        107621,
        107622,
        107623,
        107624,
        107625,
        107626,
        107627,
        107628,
        107629,
        107630,
        107631,
        107632,
        107633,
        107634,
        107635,
        107636,
        107637,
        107638,
        107639,
        107640,
        107641,
        107642,
        107643,
        107644,
        107645,
        107646,
        107647,
        107648,
        107649,
        107650,
        107651,
        107652,
        107653,
        107654,
        107655,
        107656,
        107657,
        107658,
        107659,
        107660,
        107661,
        107662,
        107663,
        107664,
        107665,
        107666,
        107667,
        107668,
        107669,
        107670,
        107671,
        107672,
        107673,
        107674,
        107675,
        107676,
        107677,
        107678,
        107679,
        107680,
        107681,
        107682,
        107683,
        107684,
        107685,
        107686,
        107687,
        107688,
        107689,
        107690,
        107691,
        107692,
        107693,
        107694,
        107695,
        107696,
        107697,
        107698,
        107699
    ],
    "job_id": 1076,
    "seed": 551424,
    "particle_name": "Jpsi",
    "run": {
        "nov": 100,
        "nov_per_job": 100,
        "run_number": 20250122,
        "seed": 512
    },
    "stages": [
        {
            "name": "step_1",
            "script": "gen_Jpsi.py",
            "extra_args": {
                "seed": "%SEED",
                "run-number": "%RUN_NUMBER",
                "event-numbers": "%EVENT_NUMBERS"
            },
            "output": "%JOB_WORKAREA/step_1/Jpsi.EVT.%JOB_ID.root"
        },
        {
            "name": "step_2",
            "script": "simu_trf.py",
            "extra_args": {
                "enable-magnetic-field": "None",
                "timeout": 30,
                "number-of-threads": "%CPU_CORES"
            },
            "input": "%JOB_WORKAREA/step_1/Jpsi.EVT.%JOB_ID.root",
            "output": "%JOB_WORKAREA/step_2/Jpsi.HIT.%JOB_ID.root"
        },
        {
            "name": "step_3",
            "script": "digit_trf.py",
            "extra_args": {},
            "input": "%JOB_WORKAREA/step_2/Jpsi.HIT.%JOB_ID.root",
            "output": "%JOB_WORKAREA/step_3/Jpsi.ESD.%JOB_ID.root"
        },
        {
            "name": "step_4",
            "script": "reco_trf.py",
            "extra_args": {},
            "input": "%JOB_WORKAREA/step_3/Jpsi.ESD.%JOB_ID.root",
            "output": "%JOB_WORKAREA/step_4/Jpsi.AOD.%JOB_ID.root"
        },
        {
            "name": "step_5",
            "script": "ntuple_trf.py",
            "extra_args": {},
            "input": "%JOB_WORKAREA/step_4/Jpsi.AOD.%JOB_ID.root",
            "output": "%JOB_WORKAREA/step_5/Jpsi.NTUP.%JOB_ID.root"
        }
    ]
}