{
    "event_numbers": [
        123400,
        123401,
        123402,
        123403,
        123404,
        123405,
        123406,
        123407,
        123408,
        123409,
        123410,
        123411,
        123412,
        123413,
        123414,
        123415,
        123416,
        123417,
        123418,
        123419,
        123420,
        123421,
        123422,
        123423,
        123424,
        123425,
        123426,
        123427,
        123428,
        123429,
        123430,
        123431,
        123432,
        123433,
        123434,
        123435,
        123436,
        123437,
        123438,
        123439,
        123440,
        123441,
        123442,
        123443,
        123444,
        123445,
        123446,
        123447,
        123448,
        123449,
        123450,
        123451,
        123452,
        123453,
        123454,
        123455,
        123456,
        123457,
        123458,
        123459,
        123460,
        123461,
        123462,
        123463,
        123464,
        123465,
        123466,
        123467,
        123468,
        123469,
        123470,
        123471,
        123472,
        123473,
        123474,
        123475,
        123476,
        123477,
        123478,
        123479,
        123480,
        123481,
        123482,
        123483,
        123484,
        123485,
        123486,
        123487,
        123488,
        123489,
        123490,
        123491,
        123492,
        123493,
        123494,
        123495,
        123496,
        123497,
        123498,
        123499
    ],
    "job_id": 1234,
    "seed": 632320,
    "particle_name": "Jpsi",
    "run": {
        "nov": 100,
        "nov_per_job": 100,
        "run_number": 20250122,
        "seed": 512
    },
    "stages": [
        {
            "name": "step_1",
            "script": "gen_Jpsi.py",
            "extra_args": {
                "seed": "%SEED",
                "run-number": "%RUN_NUMBER",
                "event-numbers": "%EVENT_NUMBERS"
            },
            "output": "%JOB_WORKAREA/step_1/Jpsi.EVT.%JOB_ID.root"
        },
        {
            "name": "step_2",
            "script": "simu_trf.py",
            "extra_args": {
                "enable-magnetic-field": "None",
                "timeout": 30,
                "number-of-threads": "%CPU_CORES"
            },
            "input": "%JOB_WORKAREA/step_1/Jpsi.EVT.%JOB_ID.root",
            "output": "%JOB_WORKAREA/step_2/Jpsi.HIT.%JOB_ID.root"
        },
        {
            "name": "step_3",
            "script": "digit_trf.py",
            "extra_args": {},
            "input": "%JOB_WORKAREA/step_2/Jpsi.HIT.%JOB_ID.root",
            "output": "%JOB_WORKAREA/step_3/Jpsi.ESD.%JOB_ID.root"
        },
        {
            "name": "step_4",
            "script": "reco_trf.py",
            "extra_args": {},
            "input": "%JOB_WORKAREA/step_3/Jpsi.ESD.%JOB_ID.root",
            "output": "%JOB_WORKAREA/step_4/Jpsi.AOD.%JOB_ID.root"
        },
        {
            "name": "step_5",
            "script": "ntuple_trf.py",
            "extra_args": {},
            "input": "%JOB_WORKAREA/step_4/Jpsi.AOD.%JOB_ID.root",
            "output": "%JOB_WORKAREA/step_5/Jpsi.NTUP.%JOB_ID.root"
        }
    ]
}