{
    "event_numbers": [
        582000,
        582001,
        582002,
        582003,
        582004,
        582005,
        582006,
        582007,
        582008,
        582009,
        582010,
        582011,
        582012,
        582013,
        582014,
        582015,
        582016,
        582017,
        582018,
        582019,
        582020,
        582021,
        582022,
        582023,
        582024,
        582025,
        582026,
        582027,
        582028,
        582029,
        582030,
        582031,
        582032,
        582033,
        582034,
        582035,
        582036,
        582037,
        582038,
        582039,
        582040,
        582041,
        582042,
        582043,
        582044,
        582045,
        582046,
        582047,
        582048,
        582049,
        582050,
        582051,
        582052,
        582053,
        582054,
        582055,
        582056,
        582057,
        582058,
        582059,
        582060,
        582061,
        582062,
        582063,
        582064,
        582065,
        582066,
        582067,
        582068,
        582069,
        582070,
        582071,
        582072,
        582073,
        582074,
        582075,
        582076,
        582077,
        582078,
        582079,
        582080,
        582081,
        582082,
        582083,
        582084,
        582085,
        582086,
        582087,
        582088,
        582089,
        582090,
        582091,
        582092,
        582093,
        582094,
        582095,
        582096,
        582097,
        582098,
        582099
    ],
    "job_id": 5820,
    "seed": 2980352,
    "particle_name": "Jpsi",
    "run": {
        "nov": 100,
        "nov_per_job": 100,
        "run_number": 20250122,
        "seed": 512
    },
    "stages": [
        {
            "name": "step_1",
            "script": "gen_Jpsi.py",
            "extra_args": {
                "seed": "%SEED",
                "run-number": "%RUN_NUMBER",
                "event-numbers": "%EVENT_NUMBERS"
            },
            "output": "%JOB_WORKAREA/step_1/Jpsi.EVT.%JOB_ID.root"
        },
        {
            "name": "step_2",
            "script": "simu_trf.py",
            "extra_args": {
                "enable-magnetic-field": "None",
                "timeout": 30,
                "number-of-threads": "%CPU_CORES"
            },
            "input": "%JOB_WORKAREA/step_1/Jpsi.EVT.%JOB_ID.root",
            "output": "%JOB_WORKAREA/step_2/Jpsi.HIT.%JOB_ID.root"
        },
        {
            "name": "step_3",
            "script": "digit_trf.py",
            "extra_args": {},
            "input": "%JOB_WORKAREA/step_2/Jpsi.HIT.%JOB_ID.root",
            "output": "%JOB_WORKAREA/step_3/Jpsi.ESD.%JOB_ID.root"
        },
        {
            "name": "step_4",
            "script": "reco_trf.py",
            "extra_args": {},
            "input": "%JOB_WORKAREA/step_3/Jpsi.ESD.%JOB_ID.root",
            "output": "%JOB_WORKAREA/step_4/Jpsi.AOD.%JOB_ID.root"
        },
        {
            "name": "step_5",
            "script": "ntuple_trf.py",
            "extra_args": {},
            "input": "%JOB_WORKAREA/step_4/Jpsi.AOD.%JOB_ID.root",
            "output": "%JOB_WORKAREA/step_5/Jpsi.NTUP.%JOB_ID.root"
        }
    ]
}