{
    "event_numbers": [
        672100,
        672101,
        672102,
        672103,
        672104,
        672105,
        672106,
        672107,
        672108,
        672109,
        672110,
        672111,
        672112,
        672113,
        672114,
        672115,
        672116,
        672117,
        672118,
        672119,
        672120,
        672121,
        672122,
        672123,
        672124,
        672125,
        672126,
        672127,
        672128,
        672129,
        672130,
        672131,
        672132,
        672133,
        672134,
        672135,
        672136,
        672137,
        672138,
        672139,
        672140,
        672141,
        672142,
        672143,
        672144,
        672145,
        672146,
        672147,
        672148,
        672149,
        672150,
        672151,
        672152,
        672153,
        672154,
        672155,
        672156,
        672157,
        672158,
        672159,
        672160,
        672161,
        672162,
        672163,
        672164,
        672165,
        672166,
        672167,
        672168,
        672169,
        672170,
        672171,
        672172,
        672173,
        672174,
        672175,
        672176,
        672177,
        672178,
        672179,
        672180,
        672181,
        672182,
        672183,
        672184,
        672185,
        672186,
        672187,
        672188,
        672189,
        672190,
        672191,
        672192,
        672193,
        672194,
        672195,
        672196,
        672197,
        672198,
        672199
    ],
    "job_id": 6721,
    "seed": 3441664,
    "particle_name": "Jpsi",
    "run": {
        "nov": 100,
        "nov_per_job": 100,
        "run_number": 20250122,
        "seed": 512
    },
    "stages": [
        {
            "name": "step_1",
            "script": "gen_Jpsi.py",
            "extra_args": {
                "seed": "%SEED",
                "run-number": "%RUN_NUMBER",
                "event-numbers": "%EVENT_NUMBERS"
            },
            "output": "%JOB_WORKAREA/step_1/Jpsi.EVT.%JOB_ID.root"
        },
        {
            "name": "step_2",
            "script": "simu_trf.py",
            "extra_args": {
                "enable-magnetic-field": "None",
                "timeout": 30,
                "number-of-threads": "%CPU_CORES"
            },
            "input": "%JOB_WORKAREA/step_1/Jpsi.EVT.%JOB_ID.root",
            "output": "%JOB_WORKAREA/step_2/Jpsi.HIT.%JOB_ID.root"
        },
        {
            "name": "step_3",
            "script": "digit_trf.py",
            "extra_args": {},
            "input": "%JOB_WORKAREA/step_2/Jpsi.HIT.%JOB_ID.root",
            "output": "%JOB_WORKAREA/step_3/Jpsi.ESD.%JOB_ID.root"
        },
        {
            "name": "step_4",
            "script": "reco_trf.py",
            "extra_args": {},
            "input": "%JOB_WORKAREA/step_3/Jpsi.ESD.%JOB_ID.root",
            "output": "%JOB_WORKAREA/step_4/Jpsi.AOD.%JOB_ID.root"
        },
        {
            "name": "step_5",
            "script": "ntuple_trf.py",
            "extra_args": {},
            "input": "%JOB_WORKAREA/step_4/Jpsi.AOD.%JOB_ID.root",
            "output": "%JOB_WORKAREA/step_5/Jpsi.NTUP.%JOB_ID.root"
        }
    ]
}