{
    "event_numbers": [
        778000,
        778001,
        778002,
        778003,
        778004,
        778005,
        778006,
        778007,
        778008,
        778009,
        778010,
        778011,
        778012,
        778013,
        778014,
        778015,
        778016,
        778017,
        778018,
        778019,
        778020,
        778021,
        778022,
        778023,
        778024,
        778025,
        778026,
        778027,
        778028,
        778029,
        778030,
        778031,
        778032,
        778033,
        778034,
        778035,
        778036,
        778037,
        778038,
        778039,
        778040,
        778041,
        778042,
        778043,
        778044,
        778045,
        778046,
        778047,
        778048,
        778049,
        778050,
        778051,
        778052,
        778053,
        778054,
        778055,
        778056,
        778057,
        778058,
        778059,
        778060,
        778061,
        778062,
        778063,
        778064,
        778065,
        778066,
        778067,
        778068,
        778069,
        778070,
        778071,
        778072,
        778073,
        778074,
        778075,
        778076,
        778077,
        778078,
        778079,
        778080,
        778081,
        778082,
        778083,
        778084,
        778085,
        778086,
        778087,
        778088,
        778089,
        778090,
        778091,
        778092,
        778093,
        778094,
        778095,
        778096,
        778097,
        778098,
        778099
    ],
    "job_id": 7780,
    "seed": 3983872,
    "particle_name": "Jpsi",
    "run": {
        "nov": 100,
        "nov_per_job": 100,
        "run_number": 20250122,
        "seed": 512
    },
    "stages": [
        {
            "name": "step_1",
            "script": "gen_Jpsi.py",
            "extra_args": {
                "seed": "%SEED",
                "run-number": "%RUN_NUMBER",
                "event-numbers": "%EVENT_NUMBERS"
            },
            "output": "%JOB_WORKAREA/step_1/Jpsi.EVT.%JOB_ID.root"
        },
        {
            "name": "step_2",
            "script": "simu_trf.py",
            "extra_args": {
                "enable-magnetic-field": "None",
                "timeout": 30,
                "number-of-threads": "%CPU_CORES"
            },
            "input": "%JOB_WORKAREA/step_1/Jpsi.EVT.%JOB_ID.root",
            "output": "%JOB_WORKAREA/step_2/Jpsi.HIT.%JOB_ID.root"
        },
        {
            "name": "step_3",
            "script": "digit_trf.py",
            "extra_args": {},
            "input": "%JOB_WORKAREA/step_2/Jpsi.HIT.%JOB_ID.root",
            "output": "%JOB_WORKAREA/step_3/Jpsi.ESD.%JOB_ID.root"
        },
        {
            "name": "step_4",
            "script": "reco_trf.py",
            "extra_args": {},
            "input": "%JOB_WORKAREA/step_3/Jpsi.ESD.%JOB_ID.root",
            "output": "%JOB_WORKAREA/step_4/Jpsi.AOD.%JOB_ID.root"
        },
        {
            "name": "step_5",
            "script": "ntuple_trf.py",
            "extra_args": {},
            "input": "%JOB_WORKAREA/step_4/Jpsi.AOD.%JOB_ID.root",
            "output": "%JOB_WORKAREA/step_5/Jpsi.NTUP.%JOB_ID.root"
        }
    ]
}