{
    "event_numbers": [
        590800,
        590801,
        590802,
        590803,
        590804,
        590805,
        590806,
        590807,
        590808,
        590809,
        590810,
        590811,
        590812,
        590813,
        590814,
        590815,
        590816,
        590817,
        590818,
        590819,
        590820,
        590821,
        590822,
        590823,
        590824,
        590825,
        590826,
        590827,
        590828,
        590829,
        590830,
        590831,
        590832,
        590833,
        590834,
        590835,
        590836,
        590837,
        590838,
        590839,
        590840,
        590841,
        590842,
        590843,
        590844,
        590845,
        590846,
        590847,
        590848,
        590849,
        590850,
        590851,
        590852,
        590853,
        590854,
        590855,
        590856,
        590857,
        590858,
        590859,
        590860,
        590861,
        590862,
        590863,
        590864,
        590865,
        590866,
        590867,
        590868,
        590869,
        590870,
        590871,
        590872,
        590873,
        590874,
        590875,
        590876,
        590877,
        590878,
        590879,
        590880,
        590881,
        590882,
        590883,
        590884,
        590885,
        590886,
        590887,
        590888,
        590889,
        590890,
        590891,
        590892,
        590893,
        590894,
        590895,
        590896,
        590897,
        590898,
        590899
    ],
    "job_id": 5908,
    "seed": 3025408,
    "particle_name": "Jpsi",
    "run": {
        "nov": 100,
        "nov_per_job": 100,
        "run_number": 20250122,
        "seed": 512
    },
    "stages": [
        {
            "name": "step_1",
            "script": "gen_Jpsi.py",
            "extra_args": {
                "seed": "%SEED",
                "run-number": "%RUN_NUMBER",
                "event-numbers": "%EVENT_NUMBERS"
            },
            "output": "%JOB_WORKAREA/step_1/Jpsi.EVT.%JOB_ID.root"
        },
        {
            "name": "step_2",
            "script": "simu_trf.py",
            "extra_args": {
                "enable-magnetic-field": "None",
                "timeout": 30,
                "number-of-threads": "%CPU_CORES"
            },
            "input": "%JOB_WORKAREA/step_1/Jpsi.EVT.%JOB_ID.root",
            "output": "%JOB_WORKAREA/step_2/Jpsi.HIT.%JOB_ID.root"
        },
        {
            "name": "step_3",
            "script": "digit_trf.py",
            "extra_args": {},
            "input": "%JOB_WORKAREA/step_2/Jpsi.HIT.%JOB_ID.root",
            "output": "%JOB_WORKAREA/step_3/Jpsi.ESD.%JOB_ID.root"
        },
        {
            "name": "step_4",
            "script": "reco_trf.py",
            "extra_args": {},
            "input": "%JOB_WORKAREA/step_3/Jpsi.ESD.%JOB_ID.root",
            "output": "%JOB_WORKAREA/step_4/Jpsi.AOD.%JOB_ID.root"
        },
        {
            "name": "step_5",
            "script": "ntuple_trf.py",
            "extra_args": {},
            "input": "%JOB_WORKAREA/step_4/Jpsi.AOD.%JOB_ID.root",
            "output": "%JOB_WORKAREA/step_5/Jpsi.NTUP.%JOB_ID.root"
        }
    ]
}