{
    "event_numbers": [
        762300,
        762301,
        762302,
        762303,
        762304,
        762305,
        762306,
        762307,
        762308,
        762309,
        762310,
        762311,
        762312,
        762313,
        762314,
        762315,
        762316,
        762317,
        762318,
        762319,
        762320,
        762321,
        762322,
        762323,
        762324,
        762325,
        762326,
        762327,
        762328,
        762329,
        762330,
        762331,
        762332,
        762333,
        762334,
        762335,
        762336,
        762337,
        762338,
        762339,
        762340,
        762341,
        762342,
        762343,
        762344,
        762345,
        762346,
        762347,
        762348,
        762349,
        762350,
        762351,
        762352,
        762353,
        762354,
        762355,
        762356,
        762357,
        762358,
        762359,
        762360,
        762361,
        762362,
        762363,
        762364,
        762365,
        762366,
        762367,
        762368,
        762369,
        762370,
        762371,
        762372,
        762373,
        762374,
        762375,
        762376,
        762377,
        762378,
        762379,
        762380,
        762381,
        762382,
        762383,
        762384,
        762385,
        762386,
        762387,
        762388,
        762389,
        762390,
        762391,
        762392,
        762393,
        762394,
        762395,
        762396,
        762397,
        762398,
        762399
    ],
    "job_id": 7623,
    "seed": 3903488,
    "run": {
        "nov": 100,
        "nov_per_job": 100,
        "run_number": 20250122,
        "seed": 512
    },
    "stages": [
        {
            "name": "step_1",
            "script": "gen_zee.py",
            "extra_args": {
                "seed": "%SEED",
                "run-number": "%RUN_NUMBER",
                "event-numbers": "%EVENT_NUMBERS"
            },
            "output": "%JOB_WORKAREA/step_1/Zee.EVT.%JOB_ID.root"
        },
        {
            "name": "step_2",
            "script": "simu_trf.py",
            "extra_args": {
                "enable-magnetic-field": "None",
                "timeout": 30,
                "number-of-threads": "%CPU_CORES"
            },
            "input": "%JOB_WORKAREA/step_1/Zee.EVT.%JOB_ID.root",
            "output": "%JOB_WORKAREA/step_2/Zee.HIT.%JOB_ID.root"
        },
        {
            "name": "step_3",
            "script": "digit_trf.py",
            "extra_args": {},
            "input": "%JOB_WORKAREA/step_2/Zee.HIT.%JOB_ID.root",
            "output": "%JOB_WORKAREA/step_3/Zee.ESD.%JOB_ID.root"
        },
        {
            "name": "step_4",
            "script": "reco_trf.py",
            "extra_args": {},
            "input": "%JOB_WORKAREA/step_3/Zee.ESD.%JOB_ID.root",
            "output": "%JOB_WORKAREA/step_4/Zee.AOD.%JOB_ID.root"
        },
        {
            "name": "step_5",
            "script": "ntuple_trf.py",
            "extra_args": {},
            "input": "%JOB_WORKAREA/step_4/Zee.AOD.%JOB_ID.root",
            "output": "%JOB_WORKAREA/step_5/Zee.%JOB_ID.root"
        }
    ]
}