{
    "event_numbers": [
        792700,
        792701,
        792702,
        792703,
        792704,
        792705,
        792706,
        792707,
        792708,
        792709,
        792710,
        792711,
        792712,
        792713,
        792714,
        792715,
        792716,
        792717,
        792718,
        792719,
        792720,
        792721,
        792722,
        792723,
        792724,
        792725,
        792726,
        792727,
        792728,
        792729,
        792730,
        792731,
        792732,
        792733,
        792734,
        792735,
        792736,
        792737,
        792738,
        792739,
        792740,
        792741,
        792742,
        792743,
        792744,
        792745,
        792746,
        792747,
        792748,
        792749,
        792750,
        792751,
        792752,
        792753,
        792754,
        792755,
        792756,
        792757,
        792758,
        792759,
        792760,
        792761,
        792762,
        792763,
        792764,
        792765,
        792766,
        792767,
        792768,
        792769,
        792770,
        792771,
        792772,
        792773,
        792774,
        792775,
        792776,
        792777,
        792778,
        792779,
        792780,
        792781,
        792782,
        792783,
        792784,
        792785,
        792786,
        792787,
        792788,
        792789,
        792790,
        792791,
        792792,
        792793,
        792794,
        792795,
        792796,
        792797,
        792798,
        792799
    ],
    "job_id": 7927,
    "seed": 4059136,
    "run": {
        "nov": 100,
        "nov_per_job": 100,
        "run_number": 20250122,
        "seed": 512
    },
    "stages": [
        {
            "name": "step_1",
            "script": "gen_zee.py",
            "extra_args": {
                "seed": "%SEED",
                "run-number": "%RUN_NUMBER",
                "event-numbers": "%EVENT_NUMBERS"
            },
            "output": "%JOB_WORKAREA/step_1/Zee.EVT.%JOB_ID.root"
        },
        {
            "name": "step_2",
            "script": "simu_trf.py",
            "extra_args": {
                "enable-magnetic-field": "None",
                "timeout": 30,
                "number-of-threads": "%CPU_CORES"
            },
            "input": "%JOB_WORKAREA/step_1/Zee.EVT.%JOB_ID.root",
            "output": "%JOB_WORKAREA/step_2/Zee.HIT.%JOB_ID.root"
        },
        {
            "name": "step_3",
            "script": "digit_trf.py",
            "extra_args": {},
            "input": "%JOB_WORKAREA/step_2/Zee.HIT.%JOB_ID.root",
            "output": "%JOB_WORKAREA/step_3/Zee.ESD.%JOB_ID.root"
        },
        {
            "name": "step_4",
            "script": "reco_trf.py",
            "extra_args": {},
            "input": "%JOB_WORKAREA/step_3/Zee.ESD.%JOB_ID.root",
            "output": "%JOB_WORKAREA/step_4/Zee.AOD.%JOB_ID.root"
        },
        {
            "name": "step_5",
            "script": "ntuple_trf.py",
            "extra_args": {},
            "input": "%JOB_WORKAREA/step_4/Zee.AOD.%JOB_ID.root",
            "output": "%JOB_WORKAREA/step_5/Zee.%JOB_ID.root"
        }
    ]
}