{
    "event_numbers": [
        112300,
        112301,
        112302,
        112303,
        112304,
        112305,
        112306,
        112307,
        112308,
        112309,
        112310,
        112311,
        112312,
        112313,
        112314,
        112315,
        112316,
        112317,
        112318,
        112319,
        112320,
        112321,
        112322,
        112323,
        112324,
        112325,
        112326,
        112327,
        112328,
        112329,
        112330,
        112331,
        112332,
        112333,
        112334,
        112335,
        112336,
        112337,
        112338,
        112339,
        112340,
        112341,
        112342,
        112343,
        112344,
        112345,
        112346,
        112347,
        112348,
        112349,
        112350,
        112351,
        112352,
        112353,
        112354,
        112355,
        112356,
        112357,
        112358,
        112359,
        112360,
        112361,
        112362,
        112363,
        112364,
        112365,
        112366,
        112367,
        112368,
        112369,
        112370,
        112371,
        112372,
        112373,
        112374,
        112375,
        112376,
        112377,
        112378,
        112379,
        112380,
        112381,
        112382,
        112383,
        112384,
        112385,
        112386,
        112387,
        112388,
        112389,
        112390,
        112391,
        112392,
        112393,
        112394,
        112395,
        112396,
        112397,
        112398,
        112399
    ],
    "job_id": 1123,
    "seed": 575488,
    "run": {
        "nov": 100,
        "nov_per_job": 100,
        "run_number": 20250122,
        "seed": 512
    },
    "stages": [
        {
            "name": "step_1",
            "script": "gen_zee.py",
            "extra_args": {
                "seed": "%SEED",
                "run-number": "%RUN_NUMBER",
                "event-numbers": "%EVENT_NUMBERS"
            },
            "output": "%JOB_WORKAREA/step_1/Zee.EVT.%JOB_ID.root"
        },
        {
            "name": "step_2",
            "script": "simu_trf.py",
            "extra_args": {
                "enable-magnetic-field": "None",
                "timeout": 30,
                "number-of-threads": "%CPU_CORES"
            },
            "input": "%JOB_WORKAREA/step_1/Zee.EVT.%JOB_ID.root",
            "output": "%JOB_WORKAREA/step_2/Zee.HIT.%JOB_ID.root"
        },
        {
            "name": "step_3",
            "script": "digit_trf.py",
            "extra_args": {},
            "input": "%JOB_WORKAREA/step_2/Zee.HIT.%JOB_ID.root",
            "output": "%JOB_WORKAREA/step_3/Zee.ESD.%JOB_ID.root"
        },
        {
            "name": "step_4",
            "script": "reco_trf.py",
            "extra_args": {},
            "input": "%JOB_WORKAREA/step_3/Zee.ESD.%JOB_ID.root",
            "output": "%JOB_WORKAREA/step_4/Zee.AOD.%JOB_ID.root"
        },
        {
            "name": "step_5",
            "script": "ntuple_trf.py",
            "extra_args": {},
            "input": "%JOB_WORKAREA/step_4/Zee.AOD.%JOB_ID.root",
            "output": "%JOB_WORKAREA/step_5/Zee.%JOB_ID.root"
        }
    ]
}