{
    "event_numbers": [
        308000,
        308001,
        308002,
        308003,
        308004,
        308005,
        308006,
        308007,
        308008,
        308009,
        308010,
        308011,
        308012,
        308013,
        308014,
        308015,
        308016,
        308017,
        308018,
        308019,
        308020,
        308021,
        308022,
        308023,
        308024,
        308025,
        308026,
        308027,
        308028,
        308029,
        308030,
        308031,
        308032,
        308033,
        308034,
        308035,
        308036,
        308037,
        308038,
        308039,
        308040,
        308041,
        308042,
        308043,
        308044,
        308045,
        308046,
        308047,
        308048,
        308049,
        308050,
        308051,
        308052,
        308053,
        308054,
        308055,
        308056,
        308057,
        308058,
        308059,
        308060,
        308061,
        308062,
        308063,
        308064,
        308065,
        308066,
        308067,
        308068,
        308069,
        308070,
        308071,
        308072,
        308073,
        308074,
        308075,
        308076,
        308077,
        308078,
        308079,
        308080,
        308081,
        308082,
        308083,
        308084,
        308085,
        308086,
        308087,
        308088,
        308089,
        308090,
        308091,
        308092,
        308093,
        308094,
        308095,
        308096,
        308097,
        308098,
        308099
    ],
    "job_id": 3080,
    "seed": 1577472,
    "run": {
        "nov": 100,
        "nov_per_job": 100,
        "run_number": 20250122,
        "seed": 512
    },
    "stages": [
        {
            "name": "step_1",
            "script": "gen_zee.py",
            "extra_args": {
                "seed": "%SEED",
                "run-number": "%RUN_NUMBER",
                "event-numbers": "%EVENT_NUMBERS"
            },
            "output": "%JOB_WORKAREA/step_1/Zee.EVT.%JOB_ID.root"
        },
        {
            "name": "step_2",
            "script": "simu_trf.py",
            "extra_args": {
                "enable-magnetic-field": "None",
                "timeout": 30,
                "number-of-threads": "%CPU_CORES"
            },
            "input": "%JOB_WORKAREA/step_1/Zee.EVT.%JOB_ID.root",
            "output": "%JOB_WORKAREA/step_2/Zee.HIT.%JOB_ID.root"
        },
        {
            "name": "step_3",
            "script": "digit_trf.py",
            "extra_args": {},
            "input": "%JOB_WORKAREA/step_2/Zee.HIT.%JOB_ID.root",
            "output": "%JOB_WORKAREA/step_3/Zee.ESD.%JOB_ID.root"
        },
        {
            "name": "step_4",
            "script": "reco_trf.py",
            "extra_args": {},
            "input": "%JOB_WORKAREA/step_3/Zee.ESD.%JOB_ID.root",
            "output": "%JOB_WORKAREA/step_4/Zee.AOD.%JOB_ID.root"
        },
        {
            "name": "step_5",
            "script": "ntuple_trf.py",
            "extra_args": {},
            "input": "%JOB_WORKAREA/step_4/Zee.AOD.%JOB_ID.root",
            "output": "%JOB_WORKAREA/step_5/Zee.%JOB_ID.root"
        }
    ]
}