{
    "event_numbers": [
        966100,
        966101,
        966102,
        966103,
        966104,
        966105,
        966106,
        966107,
        966108,
        966109,
        966110,
        966111,
        966112,
        966113,
        966114,
        966115,
        966116,
        966117,
        966118,
        966119,
        966120,
        966121,
        966122,
        966123,
        966124,
        966125,
        966126,
        966127,
        966128,
        966129,
        966130,
        966131,
        966132,
        966133,
        966134,
        966135,
        966136,
        966137,
        966138,
        966139,
        966140,
        966141,
        966142,
        966143,
        966144,
        966145,
        966146,
        966147,
        966148,
        966149,
        966150,
        966151,
        966152,
        966153,
        966154,
        966155,
        966156,
        966157,
        966158,
        966159,
        966160,
        966161,
        966162,
        966163,
        966164,
        966165,
        966166,
        966167,
        966168,
        966169,
        966170,
        966171,
        966172,
        966173,
        966174,
        966175,
        966176,
        966177,
        966178,
        966179,
        966180,
        966181,
        966182,
        966183,
        966184,
        966185,
        966186,
        966187,
        966188,
        966189,
        966190,
        966191,
        966192,
        966193,
        966194,
        966195,
        966196,
        966197,
        966198,
        966199
    ],
    "job_id": 9661,
    "seed": 4946944,
    "run": {
        "nov": 100,
        "nov_per_job": 100,
        "run_number": 20250122,
        "seed": 512
    },
    "stages": [
        {
            "name": "step_1",
            "script": "gen_zee.py",
            "extra_args": {
                "seed": "%SEED",
                "run-number": "%RUN_NUMBER",
                "event-numbers": "%EVENT_NUMBERS"
            },
            "output": "%JOB_WORKAREA/step_1/Zee.EVT.%JOB_ID.root"
        },
        {
            "name": "step_2",
            "script": "simu_trf.py",
            "extra_args": {
                "enable-magnetic-field": "None",
                "timeout": 30,
                "number-of-threads": "%CPU_CORES"
            },
            "input": "%JOB_WORKAREA/step_1/Zee.EVT.%JOB_ID.root",
            "output": "%JOB_WORKAREA/step_2/Zee.HIT.%JOB_ID.root"
        },
        {
            "name": "step_3",
            "script": "digit_trf.py",
            "extra_args": {},
            "input": "%JOB_WORKAREA/step_2/Zee.HIT.%JOB_ID.root",
            "output": "%JOB_WORKAREA/step_3/Zee.ESD.%JOB_ID.root"
        },
        {
            "name": "step_4",
            "script": "reco_trf.py",
            "extra_args": {},
            "input": "%JOB_WORKAREA/step_3/Zee.ESD.%JOB_ID.root",
            "output": "%JOB_WORKAREA/step_4/Zee.AOD.%JOB_ID.root"
        },
        {
            "name": "step_5",
            "script": "ntuple_trf.py",
            "extra_args": {},
            "input": "%JOB_WORKAREA/step_4/Zee.AOD.%JOB_ID.root",
            "output": "%JOB_WORKAREA/step_5/Zee.%JOB_ID.root"
        }
    ]
}